pyMILES/__init__.py
pyMILES/embedding.py
tests/__init__.py
tests/embedding_demo.py
tests/embedding_test.py
tests/l1_svm_demo.py
pyMILES-0.0.6.dist-info/LICENSE
pyMILES-0.0.6.dist-info/METADATA
pyMILES-0.0.6.dist-info/WHEEL
pyMILES-0.0.6.dist-info/top_level.txt
pyMILES-0.0.6.dist-info/RECORD
