Metadata-Version: 2.1
Name: pyMILES
Version: 0.0.6
Summary: Multiple instance learning via embedded instance selection
Home-page: https://github.com/johnvorsten/MILES
Author: John Vorsten
Author-email: johnvorsten@yahoo.com
Classifier: Programming Language :: Python :: 3
Classifier: License :: OSI Approved :: MIT License
Classifier: Operating System :: OS Independent
Requires-Python: >=3
License-File: LICENSE
